drf_requests_jwt/__init__.py
drf_requests_jwt/deserializers.py
drf_requests_jwt/services.py
drf_requests_jwt/settings.py
drf_requests_jwt/backends/__init__.py
drf_requests_jwt/backends/base.py
drf_requests_jwt/backends/django_cache.py
drf_requests_jwt/backends/file_cache.py
drf_requests_jwt/backends/utils.py
drf_requests_jwt/tests/__init__.py
drf_requests_jwt/tests/test_deserializers.py
drf_requests_jwt/tests/test_services.py
drf_requests_jwt-0.15.dist-info/LICENSE
drf_requests_jwt-0.15.dist-info/METADATA
drf_requests_jwt-0.15.dist-info/WHEEL
drf_requests_jwt-0.15.dist-info/top_level.txt
drf_requests_jwt-0.15.dist-info/RECORD
