Metadata-Version: 2.1
Name: drf-requests-jwt
Version: 0.15
Summary: Django Rest Framework Requests with JWT support
Home-page: https://github.com/sensidev/drf-requests-jwt
Author: Sensidev
Author-email: lucian.corduneanu@sensidev.com
License: MIT
Platform: UNKNOWN
Classifier: Development Status :: 5 - Production/Stable
Classifier: Intended Audience :: Developers
Classifier: Natural Language :: English
Classifier: License :: OSI Approved :: MIT License
Classifier: Programming Language :: Python
Classifier: Programming Language :: Python :: 3
Classifier: Programming Language :: Python :: 3.3
Classifier: Programming Language :: Python :: 3.4
Classifier: Programming Language :: Python :: 3.5
Classifier: Programming Language :: Python :: 3.6
Requires-Dist: requests (>=2.18.1)
Requires-Dist: python-slugify (>=1.2.4)
